[{"is": 1}, {"in": 2}, {"it": 3}, {"during": 4}, {"the": 5}, {"but": 6}, {"and": 7}, {"sometimes": 8}, {"usually": 9}, {"never": 10}, {"favorite": 11}, {"least": 12}, {"fruit": 13}, {"most": 14}, {"loved": 15}, {"liked": 16}, {"new": 17}, {"paris": 18}, {"california": 19}, {"france": 20}, {"india": 21}, {"he": 22}, {"she": 23}, {"china": 24}, {"united": 25}, {"states": 26}, {"jersey": 27}, {"grapefruit": 28}, {"your": 29}, {"his": 30}, {"my": 31}, {"her": 32}, {"june": 33}, {"spring": 34}, {"january": 35}, {"their": 36}, {"our": 37}, {"winter": 38}, {"december": 39}, {"july": 40}, {"april": 41}, {"february": 42}, {"nice": 43}, {"summer": 44}, {"march": 45}, {"october": 46}, {"september": 47}, {"beautiful": 48}, {"warm": 49}, {"november": 50}, {"pleasant": 51}, {"mild": 52}, {"busy": 53}, {"wet": 54}, {"chilly": 55}, {"may": 56}, {"snowy": 57}, {"freezing": 58}, {"wonderful": 59}, {"quiet": 60}, {"relaxing": 61}, {"hot": 62}, {"dry": 63}, {"cold": 64}, {"rainy": 65}, {"august": 66}, {"fall": 67}, {"autumn": 68}, {"dislikes": 69}, {"likes": 70}, {"limes": 71}, {"lemons": 72}, {"grapes": 73}, {"mangoes": 74}, {"apples": 75}, {"peaches": 76}, {"oranges": 77}, {"pears": 78}, {"strawberries": 79}, {"bananas": 80}, {"to": 81}, {"orange": 82}, {"pear": 83}, {"strawberry": 84}, {"peach": 85}, {"lemon": 86}, {"lime": 87}, {"mango": 88}, {"grape": 89}, {"apple": 90}, {"banana": 91}, {"like": 92}, {"dislike": 93}, {"they": 94}, {"that": 95}, {"i": 96}, {"we": 97}, {"you": 98}, {"animal": 99}, {"a": 100}, {"truck": 101}, {"car": 102}, {"automobile": 103}, {"was": 104}, {"next": 105}, {"go": 106}, {"driving": 107}, {"visit": 108}, {"little": 109}, {"big": 110}, {"old": 111}, {"yellow": 112}, {"red": 113}, {"rusty": 114}, {"blue": 115}, {"white": 116}, {"black": 117}, {"green": 118}, {"shiny": 119}, {"are": 120}, {"last": 121}, {"feared": 122}, {"animals": 123}, {"this": 124}, {"plan": 125}, {"going": 126}, {"saw": 127}, {"disliked": 128}, {"drives": 129}, {"drove": 130}, {"between": 131}, {"translate": 132}, {"plans": 133}, {"were": 134}, {"went": 135}, {"might": 136}, {"wanted": 137}, {"thinks": 138}, {"spanish": 139}, {"portuguese": 140}, {"chinese": 141}, {"english": 142}, {"french": 143}, {"translating": 144}, {"difficult": 145}, {"fun": 146}, {"easy": 147}, {"wants": 148}, {"think": 149}, {"why": 150}, {"its": 151}, {"did": 152}, {"cat": 153}, {"shark": 154}, {"bird": 155}, {"mouse": 156}, {"horse": 157}, {"elephant": 158}, {"dog": 159}, {"monkey": 160}, {"lion": 161}, {"bear": 162}, {"rabbit": 163}, {"snake": 164}, {"when": 165}, {"want": 166}, {"do": 167}, {"how": 168}, {"elephants": 169}, {"horses": 170}, {"dogs": 171}, {"sharks": 172}, {"snakes": 173}, {"cats": 174}, {"rabbits": 175}, {"monkeys": 176}, {"bears": 177}, {"birds": 178}, {"lions": 179}, {"mice": 180}, {"didnt": 181}, {"eiffel": 182}, {"tower": 183}, {"grocery": 184}, {"store": 185}, {"football": 186}, {"field": 187}, {"lake": 188}, {"school": 189}, {"would": 190}, {"arent": 191}, {"been": 192}, {"weather": 193}, {"does": 194}, {"has": 195}, {"isnt": 196}, {"am": 197}, {"where": 198}, {"have": 199}]